instauto/__init__.py
instauto/api/__init__.py
instauto/api/client.py
instauto/api/constants.py
instauto/api/exceptions.py
instauto/api/structs.py
instauto/api/actions/__init__.py
instauto/api/actions/activity.py
instauto/api/actions/authentication.py
instauto/api/actions/challenge.py
instauto/api/actions/direct.py
instauto/api/actions/feed.py
instauto/api/actions/friendships.py
instauto/api/actions/helpers.py
instauto/api/actions/post.py
instauto/api/actions/profile.py
instauto/api/actions/request.py
instauto/api/actions/search.py
instauto/api/actions/stub.py
instauto/api/actions/structs/__init__.py
instauto/api/actions/structs/activity.py
instauto/api/actions/structs/common.py
instauto/api/actions/structs/direct.py
instauto/api/actions/structs/feed.py
instauto/api/actions/structs/friendships.py
instauto/api/actions/structs/post.py
instauto/api/actions/structs/profile.py
instauto/api/actions/structs/search.py
instauto/bot/__init__.py
instauto/bot/bot.py
instauto/bot/input.py
instauto/helpers/__init__.py
instauto/helpers/common.py
instauto/helpers/feed.py
instauto/helpers/friendships.py
instauto/helpers/models.py
instauto/helpers/post.py
instauto/helpers/search.py
instauto-2.0.7.dist-info/LICENSE
instauto-2.0.7.dist-info/METADATA
instauto-2.0.7.dist-info/WHEEL
instauto-2.0.7.dist-info/top_level.txt
instauto-2.0.7.dist-info/RECORD
