Metadata-Version: 2.1
Name: instauto
Version: 2.0.7
Summary: Python wrapper for the private Instagram API
Home-page: https://github.com/stanvanrooy/instauto
Author: Stan van Rooy
Author-email: stan@rooy.dev
License: MIT
Download-URL: https://github.com/stanvanrooy/instauto/archive/2.0.7.tar.gz
Keywords: instagram api,private instagram api
Platform: UNKNOWN
Classifier: Development Status :: 5 - Production/Stable
Classifier: Intended Audience :: Developers
Classifier: Environment :: Console
Classifier: Topic :: Software Development :: Libraries :: Python Modules
Classifier: License :: OSI Approved :: GNU General Public License v3 (GPLv3)  
Classifier: Programming Language :: Python :: 3.8
Classifier: Programming Language :: Python :: 3.7
Classifier: Programming Language :: Python :: 3.6
Requires-Dist: requests
Requires-Dist: apscheduler
Requires-Dist: pycryptodomex
Requires-Dist: imagesize
Requires-Dist: orjson
